pygamerui/__init__.py
pygamerui/anchor.py
pygamerui/container.py
pygamerui/element.py
pygamerui/layout.py
pygamerui/layouts.py
pygamerui/widget_adapter.py
pygamerui-0.0.2.dist-info/licenses/LICENSE
pygamerui-0.0.2.dist-info/METADATA
pygamerui-0.0.2.dist-info/WHEEL
pygamerui-0.0.2.dist-info/top_level.txt
pygamerui-0.0.2.dist-info/RECORD
