Metadata-Version: 2.4
Name: pygamerui
Version: 0.0.2
Summary: A responsive GUI framework for Pygame applications
Home-page: https://github.com/wowek2/pygame-rgui
Author: Wojciech Bulcewicz
Author-email: bulcewiczwojciech@gmail.com
Classifier: Programming Language :: Python :: 3
Classifier: License :: OSI Approved :: MIT License
Classifier: Operating System :: OS Independent
Classifier: Topic :: Software Development :: Libraries
Classifier: Topic :: Games/Entertainment
Requires-Python: >=3.6
License-File: LICENSE
Requires-Dist: pygame>=2.0.0
Dynamic: license-file
Dynamic: requires-dist
Dynamic: requires-python
